echoCapture_STT/__init__.py
echoCapture_STT-1.0.dist-info/METADATA
echoCapture_STT-1.0.dist-info/WHEEL
echoCapture_STT-1.0.dist-info/top_level.txt
echoCapture_STT-1.0.dist-info/RECORD
