Metadata-Version: 2.1
Name: echoCapture_STT
Version: 1.0
Summary: This is speech to text package for youtube and other website created by Jagu Nayak
Author: Jagu Nayak
